entari_cli-0.4.0.dist-info/METADATA
entari_cli-0.4.0.dist-info/WHEEL
entari_cli-0.4.0.dist-info/entry_points.txt
entari_cli-0.4.0.dist-info/licenses/LICENSE
entari_cli/__init__.py
entari_cli/__main__.py
entari_cli/commands/__init__.py
entari_cli/commands/adapter.py
entari_cli/commands/add.py
entari_cli/commands/cfg_path.py
entari_cli/commands/generate.py
entari_cli/commands/init.py
entari_cli/commands/new.py
entari_cli/commands/remove.py
entari_cli/commands/run.py
entari_cli/commands/setting.py
entari_cli/commands/version.py
entari_cli/config.py
entari_cli/consts.py
entari_cli/i18n/.config.json
entari_cli/i18n/.lang.schema.json
entari_cli/i18n/.template.json
entari_cli/i18n/.template.schema.json
entari_cli/i18n/__init__.py
entari_cli/i18n/en-US.json
entari_cli/i18n/model.py
entari_cli/i18n/zh-CN.json
entari_cli/process.py
entari_cli/project.py
entari_cli/py_info.py
entari_cli/setting.py
entari_cli/template.py
entari_cli/utils.py
entari_cli/venv.py
entari_cli-0.4.0.dist-info/RECORD
