Metadata-Version: 2.1
Name: entari-cli
Version: 0.4.0
Summary: Entari Command Line Tool, extract from arclet.entari.__main__
Keywords: bot,dependency,entari
Author-Email: RF-Tar-Railt <rf_tar_railt@qq.com>
License: MIT
Classifier: Development Status :: 4 - Beta
Classifier: Topic :: Software Development :: Build Tools
Classifier: Framework :: Robot Framework
Classifier: Framework :: Robot Framework :: Library
Classifier: License :: OSI Approved :: MIT License
Classifier: Operating System :: OS Independent
Classifier: Programming Language :: Python :: 3
Classifier: Programming Language :: Python :: 3.9
Classifier: Programming Language :: Python :: 3.10
Classifier: Programming Language :: Python :: 3.11
Classifier: Programming Language :: Python :: 3.12
Classifier: Programming Language :: Python :: 3.13
Requires-Python: >=3.9
Requires-Dist: cli-lite>=0.11.2
Requires-Dist: colorama>=0.4.6
Requires-Dist: tomlkit>=0.13.3
Requires-Dist: ruamel-yaml>=0.18.15
Requires-Dist: python-dotenv>=1.1.1
Requires-Dist: packaging>=25.0
Requires-Dist: findpython>=0.7.0
Provides-Extra: virtualenv
Requires-Dist: virtualenv>=20.34.0; extra == "virtualenv"
